bytecodemacro/__init__.py
bytecodemacro/bytecodecompiler/CodeContext.py
bytecodemacro/bytecodecompiler/Compile.py
bytecodemacro/bytecodecompiler/Header.py
bytecodemacro/bytecodecompiler/Parse.py
bytecodemacro/bytecodecompiler/PreProcess.py
bytecodemacro/bytecodecompiler/Read.py
bytecodemacro/bytecodecompiler/Runner.py
bytecodemacro/bytecodecompiler/__init__.py
bytecodemacro/common/__init__.py
bytecodemacro/common/functional.py
bytecodemacro/meta/__init__.py
bytecodemacro/meta/add_arg.py
bytecodemacro/meta/argstest.py
bytecodemacro/meta/cloop.py
bytecodemacro/meta/constant.py
bytecodemacro/meta/goto.py
bytecodemacro/meta/macro_lib.py
bytecodemacro/meta/no_dependencies.py
bytecodemacro/meta/walrus.py
bytecodemacro/uncompile/__init__.py
bytecodemacro/uncompile/dis_wrapper.py
bytecodemacro/uncompile/main.py
bytecodemacro/uncompile/obj_handler.py
bytecodemacro/uncompile/parse_dis.py
bytecodemacro/uncompile/pre_process.py
bytecodemacro-2.1.0.dist-info/LICENSE
bytecodemacro-2.1.0.dist-info/METADATA
bytecodemacro-2.1.0.dist-info/WHEEL
bytecodemacro-2.1.0.dist-info/top_level.txt
bytecodemacro-2.1.0.dist-info/RECORD
