Metadata-Version: 2.1
Name: bytecodemacro
Version: 2.1.0
Summary: a macro library that expoes the bytecode of python
Home-page: https://github.com/Glubs9/bytecodemacro
Author: glubs9
Author-email: jonte.fry@gmail.com
License: GPLv3
Platform: UNKNOWN
